nbanim/__init__.py
nbanim/core.py
nbanim-20240727162435.dist-info/METADATA
nbanim-20240727162435.dist-info/WHEEL
nbanim-20240727162435.dist-info/entry_points.txt
nbanim-20240727162435.dist-info/top_level.txt
nbanim-20240727162435.dist-info/RECORD
