Metadata-Version: 2.1
Name: nbanim
Version: 20240727162435
Summary: A utility for displaying image sequences as animations in Jupyter Notebooks.
Author-email: Hamid Ali Syed <windcirculation@gmail.com>
Requires-Python: >=3.6
Requires-Dist: ipywidgets >=7.5
Requires-Dist: IPython >=7.16
Requires-Dist: Sphinx >=4.0.2
Requires-Dist: myst-parser >=0.15.2
Requires-Dist: nbsphinx >=0.8.7
Requires-Dist: nbconvert >=6.1.0
Requires-Dist: pydata-sphinx-theme >=0.6.3
Provides-Extra: dev
Requires-Dist: flake8 >=3.9.0 ; extra == 'dev'
Requires-Dist: black >=21.5b0 ; extra == 'dev'
Requires-Dist: isort >=5.8.0 ; extra == 'dev'
